{
  "archivos": [
    {
      "titulo": "Creación de un plan de estudio",
      "descripcion": "Creado a partir de un prompt con todos los detalles",
      "vinculo": "archivos/plan de clase_generado.html"
    },
    {
      "titulo": "Creación de lista de preguntas",
      "descripcion": "Preguntas para debatir en el aula de clase",
      "vinculo": "archivos/lista_preguntas.html"
    },
    {
      "titulo": "Escibir rúbrica de evaluación",
      "descripcion": "Solicitar una rúbrica para evaluar una unidad",
      "vinculo": "archivos/rubrica.html"
    },
{
      "titulo": "Profesor personal",
      "descripcion": "Aprende cualquier habilidad en poco tiempo",
      "vinculo": "archivos/profesor_personal.html"
    },
{
      "titulo": "Plan clase de un tema",
      "descripcion": "Creación de un plan de clase por tiempo y estructurado",
      "vinculo": "archivos/plan_clase_tema.html"
    },
    {
      "titulo": "Prompts Jonathan Moreno",
      "descripcion": "Prompts para el minitaller",
      "vinculo": "archivos/Prompts Jonathan Moreno.html"
    },
    {
      "titulo": "Prompts Jorge Ojeda",
      "descripcion": "Prompts Jorge Ojeda",
      "vinculo": "archivos/Prompts Jorge Ojeda.html"
    },
       {
      "titulo": "Prompts Yeisel Jiron",
      "descripcion": "Prompts Yeisel Jiron",
      "vinculo": "archivos/Prompts Yeisel Jiron.html"
    },
      {
      "titulo": "Prompts Dulce Amador",
      "descripcion": "Prompts Dulce Amador",
      "vinculo": "archivos/Prompts Dulce Amador.html"
    },
     {
      "titulo": "Prompts Lisseth Méndez",
      "descripcion": "Prompts Lisseth Méndez",
      "vinculo": "archivos/prompts Lisseth Méndez.html"
    },
    {
      "titulo": "Prompts Deymer Acevedo",
      "descripcion": "Prompts Deymer Acevedo",
      "vinculo": "archivos/Prompts Deymer Acevedo.html"
    },
    {
      "titulo": "Prompts Carmen Castrillo",
      "descripcion": "Prompts Carmen Castrillo",
      "vinculo": "archivos/Prompts Carmen Castrillo.html"
    }

  ]
}
